{
  "image": "data_ocr/images/デジタル時計-1_OCR用.jpg",
  "all_lines": [
    {
      "text": "esc",
      "bounding_polygon": [
        {
          "x": 4346,
          "y": 2284
        },
        {
          "x": 4432,
          "y": 2298
        },
        {
          "x": 4426,
          "y": 2336
        },
        {
          "x": 4342,
          "y": 2324
        }
      ],
      "words": [
        {
          "text": "esc",
          "confidence": 0.996,
          "bounding_polygon": [
            {
              "x": 4354,
              "y": 2284
            },
            {
              "x": 4427,
              "y": 2295
            },
            {
              "x": 4421,
              "y": 2334
            },
            {
              "x": 4348,
              "y": 2323
            }
          ]
        }
      ]
    },
    {
      "text": "IN",
      "bounding_polygon": [
        {
          "x": 4908,
          "y": 2504
        },
        {
          "x": 4888,
          "y": 2554
        },
        {
          "x": 4850,
          "y": 2544
        },
        {
          "x": 4868,
          "y": 2496
        }
      ],
      "words": [
        {
          "text": "IN",
          "confidence": 0.408,
          "bounding_polygon": [
            {
              "x": 4909,
              "y": 2504
            },
            {
              "x": 4895,
              "y": 2541
            },
            {
              "x": 4857,
              "y": 2527
            },
            {
              "x": 4872,
              "y": 2496
            }
          ]
        }
      ]
    },
    {
      "text": "V A",
      "bounding_polygon": [
        {
          "x": 4444,
          "y": 2394
        },
        {
          "x": 4396,
          "y": 2488
        },
        {
          "x": 4360,
          "y": 2474
        },
        {
          "x": 4406,
          "y": 2384
        }
      ],
      "words": [
        {
          "text": "V",
          "confidence": 0.598,
          "bounding_polygon": [
            {
              "x": 4440,
              "y": 2405
            },
            {
              "x": 4430,
              "y": 2426
            },
            {
              "x": 4394,
              "y": 2407
            },
            {
              "x": 4405,
              "y": 2387
            }
          ]
        },
        {
          "text": "A",
          "confidence": 0.656,
          "bounding_polygon": [
            {
              "x": 4411,
              "y": 2462
            },
            {
              "x": 4401,
              "y": 2483
            },
            {
              "x": 4365,
              "y": 2464
            },
            {
              "x": 4375,
              "y": 2444
            }
          ]
        }
      ]
    },
    {
      "text": "5",
      "bounding_polygon": [
        {
          "x": 4224,
          "y": 2410
        },
        {
          "x": 4264,
          "y": 2422
        },
        {
          "x": 4256,
          "y": 2458
        },
        {
          "x": 4214,
          "y": 2450
        }
      ],
      "words": [
        {
          "text": "5",
          "confidence": 0.454,
          "bounding_polygon": [
            {
              "x": 4229,
              "y": 2411
            },
            {
              "x": 4251,
              "y": 2416
            },
            {
              "x": 4241,
              "y": 2455
            },
            {
              "x": 4219,
              "y": 2450
            }
          ]
        }
      ]
    },
    {
      "text": "7",
      "bounding_polygon": [
        {
          "x": 4538,
          "y": 2456
        },
        {
          "x": 4558,
          "y": 2464
        },
        {
          "x": 4558,
          "y": 2506
        },
        {
          "x": 4530,
          "y": 2498
        }
      ],
      "words": [
        {
          "text": "7",
          "confidence": 0.649,
          "bounding_polygon": [
            {
              "x": 4543,
              "y": 2456
            },
            {
              "x": 4560,
              "y": 2464
            },
            {
              "x": 4552,
              "y": 2504
            },
            {
              "x": 4530,
              "y": 2496
            }
          ]
        }
      ]
    },
    {
      "text": ".",
      "bounding_polygon": [
        {
          "x": 4102,
          "y": 2644
        },
        {
          "x": 4140,
          "y": 2662
        },
        {
          "x": 4126,
          "y": 2704
        },
        {
          "x": 4084,
          "y": 2690
        }
      ],
      "words": [
        {
          "text": ".",
          "confidence": 0.8,
          "bounding_polygon": [
            {
              "x": 4109,
              "y": 2646
            },
            {
              "x": 4136,
              "y": 2656
            },
            {
              "x": 4117,
              "y": 2703
            },
            {
              "x": 4091,
              "y": 2692
            }
          ]
        }
      ]
    },
    {
      "text": "-",
      "bounding_polygon": [
        {
          "x": 4370,
          "y": 2896
        },
        {
          "x": 4344,
          "y": 2960
        },
        {
          "x": 4312,
          "y": 2950
        },
        {
          "x": 4338,
          "y": 2884
        }
      ],
      "words": [
        {
          "text": "-",
          "confidence": 0.959,
          "bounding_polygon": [
            {
              "x": 4371,
              "y": 2896
            },
            {
              "x": 4363,
              "y": 2914
            },
            {
              "x": 4332,
              "y": 2902
            },
            {
              "x": 4339,
              "y": 2884
            }
          ]
        }
      ]
    },
    {
      "text": "[+]1",
      "bounding_polygon": [
        {
          "x": 1240,
          "y": 2550
        },
        {
          "x": 1460,
          "y": 2576
        },
        {
          "x": 1442,
          "y": 2644
        },
        {
          "x": 1210,
          "y": 2630
        }
      ],
      "words": [
        {
          "text": "[+]1",
          "confidence": 0.564,
          "bounding_polygon": [
            {
              "x": 1253,
              "y": 2550
            },
            {
              "x": 1451,
              "y": 2567
            },
            {
              "x": 1443,
              "y": 2646
            },
            {
              "x": 1245,
              "y": 2633
            }
          ]
        }
      ]
    },
    {
      "text": "Logo!",
      "bounding_polygon": [
        {
          "x": 4,
          "y": 3018
        },
        {
          "x": 632,
          "y": 2950
        },
        {
          "x": 650,
          "y": 3116
        },
        {
          "x": 16,
          "y": 3188
        }
      ],
      "words": [
        {
          "text": "Logo!",
          "confidence": 0.597,
          "bounding_polygon": [
            {
              "x": 77,
              "y": 3013
            },
            {
              "x": 622,
              "y": 2951
            },
            {
              "x": 642,
              "y": 3121
            },
            {
              "x": 90,
              "y": 3182
            }
          ]
        }
      ]
    }
  ],
  "numeric": [
    {
      "text": "5",
      "bounding_polygon": [
        {
          "x": 4224,
          "y": 2410
        },
        {
          "x": 4264,
          "y": 2422
        },
        {
          "x": 4256,
          "y": 2458
        },
        {
          "x": 4214,
          "y": 2450
        }
      ],
      "words": [
        {
          "text": "5",
          "confidence": 0.454,
          "bounding_polygon": [
            {
              "x": 4229,
              "y": 2411
            },
            {
              "x": 4251,
              "y": 2416
            },
            {
              "x": 4241,
              "y": 2455
            },
            {
              "x": 4219,
              "y": 2450
            }
          ]
        }
      ],
      "normalized": "5"
    },
    {
      "text": "7",
      "bounding_polygon": [
        {
          "x": 4538,
          "y": 2456
        },
        {
          "x": 4558,
          "y": 2464
        },
        {
          "x": 4558,
          "y": 2506
        },
        {
          "x": 4530,
          "y": 2498
        }
      ],
      "words": [
        {
          "text": "7",
          "confidence": 0.649,
          "bounding_polygon": [
            {
              "x": 4543,
              "y": 2456
            },
            {
              "x": 4560,
              "y": 2464
            },
            {
              "x": 4552,
              "y": 2504
            },
            {
              "x": 4530,
              "y": 2496
            }
          ]
        }
      ],
      "normalized": "7"
    },
    {
      "text": ".",
      "bounding_polygon": [
        {
          "x": 4102,
          "y": 2644
        },
        {
          "x": 4140,
          "y": 2662
        },
        {
          "x": 4126,
          "y": 2704
        },
        {
          "x": 4084,
          "y": 2690
        }
      ],
      "words": [
        {
          "text": ".",
          "confidence": 0.8,
          "bounding_polygon": [
            {
              "x": 4109,
              "y": 2646
            },
            {
              "x": 4136,
              "y": 2656
            },
            {
              "x": 4117,
              "y": 2703
            },
            {
              "x": 4091,
              "y": 2692
            }
          ]
        }
      ],
      "normalized": "."
    },
    {
      "text": "-",
      "bounding_polygon": [
        {
          "x": 4370,
          "y": 2896
        },
        {
          "x": 4344,
          "y": 2960
        },
        {
          "x": 4312,
          "y": 2950
        },
        {
          "x": 4338,
          "y": 2884
        }
      ],
      "words": [
        {
          "text": "-",
          "confidence": 0.959,
          "bounding_polygon": [
            {
              "x": 4371,
              "y": 2896
            },
            {
              "x": 4363,
              "y": 2914
            },
            {
              "x": 4332,
              "y": 2902
            },
            {
              "x": 4339,
              "y": 2884
            }
          ]
        }
      ],
      "normalized": "-"
    }
  ]
}