{
  "image": "data_ocr/images/デジタル時計-5_OCR用.jpg",
  "all_lines": [
    {
      "text": "15:48:21",
      "bounding_polygon": [
        {
          "x": 2782,
          "y": 466
        },
        {
          "x": 4722,
          "y": 498
        },
        {
          "x": 4720,
          "y": 1060
        },
        {
          "x": 2782,
          "y": 1058
        }
      ],
      "words": [
        {
          "text": "15:48:21",
          "confidence": 0.99,
          "bounding_polygon": [
            {
              "x": 2783,
              "y": 468
            },
            {
              "x": 4703,
              "y": 517
            },
            {
              "x": 4719,
              "y": 1060
            },
            {
              "x": 2783,
              "y": 1060
            }
          ]
        }
      ]
    },
    {
      "text": "15:48:21",
      "bounding_polygon": [
        {
          "x": 912,
          "y": 2164
        },
        {
          "x": 2120,
          "y": 2044
        },
        {
          "x": 2158,
          "y": 2420
        },
        {
          "x": 950,
          "y": 2544
        }
      ],
      "words": [
        {
          "text": "15:48:21",
          "confidence": 0.945,
          "bounding_polygon": [
            {
              "x": 912,
              "y": 2164
            },
            {
              "x": 2112,
              "y": 2044
            },
            {
              "x": 2157,
              "y": 2420
            },
            {
              "x": 952,
              "y": 2546
            }
          ]
        }
      ]
    },
    {
      "text": "MacBook Pro",
      "bounding_polygon": [
        {
          "x": 1758,
          "y": 3228
        },
        {
          "x": 1900,
          "y": 3212
        },
        {
          "x": 1904,
          "y": 3242
        },
        {
          "x": 1762,
          "y": 3262
        }
      ],
      "words": [
        {
          "text": "MacBook",
          "confidence": 0.69,
          "bounding_polygon": [
            {
              "x": 1760,
              "y": 3230
            },
            {
              "x": 1856,
              "y": 3216
            },
            {
              "x": 1862,
              "y": 3244
            },
            {
              "x": 1763,
              "y": 3263
            }
          ]
        },
        {
          "text": "Pro",
          "confidence": 0.99,
          "bounding_polygon": [
            {
              "x": 1862,
              "y": 3216
            },
            {
              "x": 1896,
              "y": 3213
            },
            {
              "x": 1903,
              "y": 3241
            },
            {
              "x": 1868,
              "y": 3244
            }
          ]
        }
      ]
    }
  ],
  "numeric": [
    {
      "text": "15:48:21",
      "bounding_polygon": [
        {
          "x": 2782,
          "y": 466
        },
        {
          "x": 4722,
          "y": 498
        },
        {
          "x": 4720,
          "y": 1060
        },
        {
          "x": 2782,
          "y": 1058
        }
      ],
      "words": [
        {
          "text": "15:48:21",
          "confidence": 0.99,
          "bounding_polygon": [
            {
              "x": 2783,
              "y": 468
            },
            {
              "x": 4703,
              "y": 517
            },
            {
              "x": 4719,
              "y": 1060
            },
            {
              "x": 2783,
              "y": 1060
            }
          ]
        }
      ],
      "normalized": "15:48:21"
    },
    {
      "text": "15:48:21",
      "bounding_polygon": [
        {
          "x": 912,
          "y": 2164
        },
        {
          "x": 2120,
          "y": 2044
        },
        {
          "x": 2158,
          "y": 2420
        },
        {
          "x": 950,
          "y": 2544
        }
      ],
      "words": [
        {
          "text": "15:48:21",
          "confidence": 0.945,
          "bounding_polygon": [
            {
              "x": 912,
              "y": 2164
            },
            {
              "x": 2112,
              "y": 2044
            },
            {
              "x": 2157,
              "y": 2420
            },
            {
              "x": 952,
              "y": 2546
            }
          ]
        }
      ],
      "normalized": "15:48:21"
    }
  ],
  "preprocessing": {
    "used_preprocessing": true,
    "attempts": 1,
    "final_stage": "attempt_1"
  }
}